easy_grid/__init__.py
easy_grid/experiences_manager.py
easy_grid/jinja2_templates/grid_template.j2
easy_grid_wdroz-0.0.8.dist-info/METADATA
easy_grid_wdroz-0.0.8.dist-info/WHEEL
easy_grid_wdroz-0.0.8.dist-info/top_level.txt
easy_grid_wdroz-0.0.8.dist-info/RECORD
