Metadata-Version: 2.1
Name: easy-grid-wdroz
Version: 0.0.8
Summary: Internal tools to use the SGE grid at Idiap Research Institute
Home-page: https://gitlab.idiap.ch/devel/easy_grid
Author: William Droz
Author-email: william.droz@idiap.ch
License: UNKNOWN
Platform: UNKNOWN
Classifier: Programming Language :: Python :: 3
Classifier: License :: OSI Approved :: MIT License
Requires-Python: >=3.5
Requires-Dist: jinja2 (>=2.10)
